pytextgrid/Intensity.py
pytextgrid/PraatTextGrid.py
pytextgrid/PraatTierIterator.py
pytextgrid/__init__.py
pytextgrid/get_named_value.py
pytextgrid/timeside2praat.py
pytextgrid-0.1.4.data/data/LICENSE
pytextgrid-0.1.4.dist-info/LICENSE
pytextgrid-0.1.4.dist-info/METADATA
pytextgrid-0.1.4.dist-info/WHEEL
pytextgrid-0.1.4.dist-info/top_level.txt
pytextgrid-0.1.4.dist-info/RECORD
